pyang_jnc/__init__.py
pyang_jnc/jnc.py
pyang_jnc-1.1.0.dist-info/AUTHORS
pyang_jnc-1.1.0.dist-info/LICENSE
pyang_jnc-1.1.0.dist-info/METADATA
pyang_jnc-1.1.0.dist-info/WHEEL
pyang_jnc-1.1.0.dist-info/entry_points.txt
pyang_jnc-1.1.0.dist-info/pbr.json
pyang_jnc-1.1.0.dist-info/top_level.txt
pyang_jnc-1.1.0.dist-info/RECORD
